LICENSE.txt
MANIFEST.in
README.md
setup.cfg
setup.py
ecapy/__init__.py
ecapy.egg-info/PKG-INFO
ecapy.egg-info/SOURCES.txt
ecapy.egg-info/dependency_links.txt
ecapy.egg-info/requires.txt
ecapy.egg-info/top_level.txt
ecapy/__pycache__/__init__.cpython-35.pyc
test/test_all.py