Metadata-Version: 1.2
Name: ecapy
Version: 1.0.1
Summary: Evolutionary Centers Algorithm: Module for Python coded in C
Home-page: https://github.com/jmejia8/ecapy
Author: Jesus Mejia
Author-email: jesusmejded@gmail.com
License: MIT
Project-URL: Source, https://github.com/jmejia8/ecapy/
Project-URL: Bug Reports, https://github.com/jmejia8/ecapy/issues
Keywords: optimization evolutionary metaheuristic
Platform: UNKNOWN
Classifier: Development Status :: 4 - Beta
Classifier: Intended Audience :: Developers
Classifier: Topic :: Software Development :: Build Tools
Classifier: License :: OSI Approved :: MIT License
Classifier: Programming Language :: Python :: 3
Classifier: Programming Language :: Python :: 3.4
Classifier: Programming Language :: Python :: 3.5
Classifier: Programming Language :: Python :: 3.6
